openqdc/__init__.py
openqdc/_version.py
openqdc/cli.py
openqdc/datasets/__init__.py
openqdc/datasets/base.py
openqdc/datasets/energies.py
openqdc/datasets/io.py
openqdc/datasets/properties.py
openqdc/datasets/statistics.py
openqdc/datasets/structure.py
openqdc/datasets/interaction/__init__.py
openqdc/datasets/interaction/_utils.py
openqdc/datasets/interaction/base.py
openqdc/datasets/interaction/des.py
openqdc/datasets/interaction/dummy.py
openqdc/datasets/interaction/l7.py
openqdc/datasets/interaction/metcalf.py
openqdc/datasets/interaction/splinter.py
openqdc/datasets/interaction/x40.py
openqdc/datasets/potential/__init__.py
openqdc/datasets/potential/alchemy.py
openqdc/datasets/potential/ani.py
openqdc/datasets/potential/comp6.py
openqdc/datasets/potential/dummy.py
openqdc/datasets/potential/gdml.py
openqdc/datasets/potential/geom.py
openqdc/datasets/potential/iso_17.py
openqdc/datasets/potential/md22.py
openqdc/datasets/potential/molecule3d.py
openqdc/datasets/potential/multixcqm9.py
openqdc/datasets/potential/nabladft.py
openqdc/datasets/potential/orbnet_denali.py
openqdc/datasets/potential/pcqm.py
openqdc/datasets/potential/proteinfragments.py
openqdc/datasets/potential/qm1b.py
openqdc/datasets/potential/qm7x.py
openqdc/datasets/potential/qmugs.py
openqdc/datasets/potential/qmx.py
openqdc/datasets/potential/revmd17.py
openqdc/datasets/potential/sn2_rxn.py
openqdc/datasets/potential/solvated_peptides.py
openqdc/datasets/potential/spice.py
openqdc/datasets/potential/tmqm.py
openqdc/datasets/potential/transition1x.py
openqdc/datasets/potential/vqm24.py
openqdc/datasets/potential/waterclusters.py
openqdc/datasets/potential/waterclusters3_30.py
openqdc/methods/__init__.py
openqdc/methods/atom_energies.py
openqdc/methods/atom_energies.txt
openqdc/methods/enums.py
openqdc/raws/pubchemqc.py
openqdc/utils/__init__.py
openqdc/utils/constants.py
openqdc/utils/descriptors.py
openqdc/utils/download_api.py
openqdc/utils/exceptions.py
openqdc/utils/io.py
openqdc-0.1.2.dist-info/LICENSE
openqdc-0.1.2.dist-info/METADATA
openqdc-0.1.2.dist-info/WHEEL
openqdc-0.1.2.dist-info/entry_points.txt
openqdc-0.1.2.dist-info/top_level.txt
openqdc-0.1.2.dist-info/RECORD
