Metadata-Version: 2.1
Name: openqdc
Version: 0.1.2
Summary: ML ready Quantum Mechanical datasets
Author-email: Nikhil Shenoy <nikhilshenoy98@gmail.com>, Prudencio Tossou <tossouprudencio@gmail.com>, Cristian Gabellini <cris.gabellini@gmail.com>
License: CC BY-NC 4.0
Project-URL: Website, https://openqdc.io
Project-URL: Source Code, https://github.com/valence-labs/openQDC
Project-URL: Bug Tracker, https://github.com/valence-labs/openQDC/issues
Project-URL: Documentation, https://docs.openqdc.io
Classifier: Development Status :: 4 - Beta
Classifier: Intended Audience :: Developers
Classifier: Intended Audience :: Healthcare Industry
Classifier: Intended Audience :: Science/Research
Classifier: Topic :: Scientific/Engineering :: Artificial Intelligence
Classifier: Topic :: Scientific/Engineering :: Bio-Informatics
Classifier: Topic :: Scientific/Engineering :: Information Analysis
Classifier: Topic :: Scientific/Engineering :: Medical Science Apps.
Classifier: Natural Language :: English
Classifier: Operating System :: OS Independent
Classifier: Programming Language :: Python
Classifier: Programming Language :: Python :: 3
Classifier: Programming Language :: Python :: 3.8
Classifier: Programming Language :: Python :: 3.9
Classifier: Programming Language :: Python :: 3.10
Classifier: Programming Language :: Python :: 3.11
Requires-Python: >=3.8
License-File: LICENSE
Requires-Dist: tqdm
Requires-Dist: pyyaml
Requires-Dist: loguru
Requires-Dist: fsspec<=2023.12.2
Requires-Dist: gcsfs
Requires-Dist: typer
Requires-Dist: prettytable
Requires-Dist: pandas
Requires-Dist: numpy
Requires-Dist: datamol
Requires-Dist: rdkit
Requires-Dist: ase
Requires-Dist: gdown
Requires-Dist: h5py>=3.8.0
Requires-Dist: dscribe
Requires-Dist: zarr
Requires-Dist: python-dotenv
Requires-Dist: s3fs
Requires-Dist: httpx
Provides-Extra: dev
Requires-Dist: pytest>=6.0; extra == "dev"
Requires-Dist: pytest-cov; extra == "dev"
Requires-Dist: nbconvert; extra == "dev"
Requires-Dist: black>=24; extra == "dev"
Requires-Dist: jupyterlab; extra == "dev"
Requires-Dist: pre-commit; extra == "dev"
Requires-Dist: ruff; extra == "dev"
Requires-Dist: mkdocs; extra == "dev"
Requires-Dist: mkdocs-material; extra == "dev"
Requires-Dist: mkdocs-material-extensions; extra == "dev"
Requires-Dist: mkdocstrings; extra == "dev"
Requires-Dist: mkdocs-click; extra == "dev"
Requires-Dist: mkdocs-jupyter; extra == "dev"
Requires-Dist: markdown-include; extra == "dev"
Requires-Dist: mdx-truly-sane-lists; extra == "dev"
Requires-Dist: mkdocstrings-python; extra == "dev"
